aws_keys_sectool/__init__.py
aws_keys_sectool/__main__.py
aws_keys_sectool/common.py
aws_keys_sectool/list_keys.py
aws_keys_sectool/protect_keys.py
aws_keys_sectool-0.3.0.dist-info/LICENSE
aws_keys_sectool-0.3.0.dist-info/METADATA
aws_keys_sectool-0.3.0.dist-info/WHEEL
aws_keys_sectool-0.3.0.dist-info/entry_points.txt
aws_keys_sectool-0.3.0.dist-info/top_level.txt
aws_keys_sectool-0.3.0.dist-info/RECORD
